<?xml version="1.0" encoding="UTF-8"?>
<worktrackerdatabase>
  <version>1.0</version>
  <tasks>
    <item name="f00" last_used="2014-04-12" id="0"/>
    <item name="n00dl" last_used="2012-04-12" id="1"/>
    <item name="p00dl" last_used="2013-04-12" id="2"/>
    <item last_used="2013-04-16" name="schneedl" id="3"/>
    <item last_used="2014-04-27" name="VM Gestartet" id="4"/>
    <item last_used="2014-04-27" name="2nd Monitor aktiviert" id="5"/>
    <item last_used="2014-04-27" name="Xubuntu Update" id="6"/>
  </tasks>
  <workdays/>
</worktrackerdatabase>
